humanfriendly-stubs/METADATA.toml
humanfriendly-stubs/__init__.pyi
humanfriendly-stubs/case.pyi
humanfriendly-stubs/cli.pyi
humanfriendly-stubs/compat.pyi
humanfriendly-stubs/decorators.pyi
humanfriendly-stubs/deprecation.pyi
humanfriendly-stubs/prompts.pyi
humanfriendly-stubs/py.typed
humanfriendly-stubs/sphinx.pyi
humanfriendly-stubs/tables.pyi
humanfriendly-stubs/testing.pyi
humanfriendly-stubs/text.pyi
humanfriendly-stubs/usage.pyi
humanfriendly-stubs/terminal/__init__.pyi
humanfriendly-stubs/terminal/html.pyi
humanfriendly-stubs/terminal/spinners.pyi
types_humanfriendly-10.0.1.20250319.dist-info/LICENSE
types_humanfriendly-10.0.1.20250319.dist-info/METADATA
types_humanfriendly-10.0.1.20250319.dist-info/WHEEL
types_humanfriendly-10.0.1.20250319.dist-info/top_level.txt
types_humanfriendly-10.0.1.20250319.dist-info/RECORD
